Workbook
Name aporte: Invest!$D$16
Name patrimonio: Invest!$D$19
Name qtd_anos: Invest!$D$17
Name rendimento_carteira: Invest!$D$12
Name salario: Invest!$D$11
Name sugestao_investimento: Invest!$D$13
Name taxa_mensal: Invest!$D$18

Sheet Invest
B10: CONFIGURAÇÕES
B11: Salário | D11: 4200
B12: Rendimento Carteira | D12: 0.006
B13: Sugestão de Investimento (30%) | D13: =D11*30% -> 1260
B15: INVESTIMENTO MENSAL
B16: Quanto investir por mês ? | D16: 1260
B17: Por Quantos Anos ? | D17: 10
B18: Taxa de Rendimento mensal ? | D18: 0.01079
B19: Patrimônio acumulado ? | D19: =FV(taxa_mensal,qtd_anos*12,aporte*-1) -> 306538.11
B20: Dividendos Mensais ? | D20: =patrimonio*rendimento_carteira -> 1839.2286
B22: Cenários | D22: Dividendo
A23: 2 | B23: Quanto em 2 Anos ? | C23: =FV($D$18,$A23*12,$D$16*-1) -> 34306.81 | D23: =C23*rendimento_carteira -> 205.84086
A24: 5 | B24: Quanto em 5 Anos ? | C24: =FV($D$18,$A24*12,$D$16*-1) -> 105558.91 | D24: =C24*rendimento_carteira -> 633.35347
A25: 10 | B25: Quanto em 10 Anos ? | C25: =FV($D$18,$A25*12,$D$16*-1) -> 306538.11 | D25: =C25*rendimento_carteira -> 1839.2286
A26: 20 | B26: Quanto em 20 Anos ? | C26: =FV($D$18,$A26*12,$D$16*-1) -> 1417750 | D26: =C26*rendimento_carteira -> 8506.4999
A27: 30 | B27: Quanto em 30 Anos ? | C27: =FV($D$18,$A27*12,$D$16*-1) -> 5445933.8 | D27: =C27*rendimento_carteira -> 32675.603
B30: PERFIL | C30: Agressivo
B31: VALOR A SER INVESTIDO POR MÊS | C31: =aporte -> 1260
B33: TIPO DE FII | C33: Percentual Sugerido | D33: Valores
B34: PAPEL | C34: =VLOOKUP($C$30&"-"&B34,Planilha2!$A$1:$D$19,4,FALSE) -> 0.5 | D34: =C34*$C$31 -> 630
B35: TIJOLO | C35: =VLOOKUP($C$30&"-"&B35,Planilha2!$A$1:$D$19,4,FALSE) -> 0.1 | D35: =C35*$C$31 -> 126
B36: HÍBRIDOS | C36: =VLOOKUP($C$30&"-"&B36,Planilha2!$A$1:$D$19,4,FALSE) -> 0.05 | D36: =C36*$C$31 -> 63
B37: FOFs | C37: =VLOOKUP($C$30&"-"&B37,Planilha2!$A$1:$D$19,4,FALSE) -> 0.05 | D37: =C37*$C$31 -> 63
B38: DESENVOLVIMENTO | C38: =VLOOKUP($C$30&"-"&B38,Planilha2!$A$1:$D$19,4,FALSE) -> 0.2 | D38: =C38*$C$31 -> 252
B39: HOTELARIAS | C39: =VLOOKUP($C$30&"-"&B39,Planilha2!$A$1:$D$19,4,FALSE) -> 0.1 | D39: =C39*$C$31 -> 126
D40: =SUM(D34:D39) -> 1260

Sheet Planilha2
A1: CHAVE | B1: PERFIL | C1: TIPO DE FII | D1: %
A2: =B2&"-"&C2 -> Conservador-PAPEL | B2: Conservador | C2: PAPEL | D2: 0.3 | H2: %
A3: =B3&"-"&C3 -> Conservador-TIJOLO | B3: Conservador | C3: TIJOLO | D3: 0.5 | G3: Moderado-TIJOLO | H3: =VLOOKUP(G3,$A:$D,4,FALSE) -> 0.35
A4: =B4&"-"&C4 -> Conservador-HÍBRIDOS | B4: Conservador | C4: HÍBRIDOS | D4: 0.1
A5: =B5&"-"&C5 -> Conservador-FOFs | B5: Conservador | C5: FOFs | D5: 0.1
A6: =B6&"-"&C6 -> Conservador-DESENVOLVIMENTO | B6: Conservador | C6: DESENVOLVIMENTO | D6: 0
A7: =B7&"-"&C7 -> Conservador-HOTELARIAS | B7: Conservador | C7: HOTELARIAS | D7: 0
A8: =B8&"-"&C8 -> Moderado-PAPEL | B8: Moderado | C8: PAPEL | D8: 0.32
A9: =B9&"-"&C9 -> Moderado-TIJOLO | B9: Moderado | C9: TIJOLO | D9: 0.35
A10: =B10&"-"&C10 -> Moderado-HÍBRIDOS | B10: Moderado | C10: HÍBRIDOS | D10: 0.08
A11: =B11&"-"&C11 -> Moderado-FOFs | B11: Moderado | C11: FOFs | D11: 0.05
A12: =B12&"-"&C12 -> Moderado-DESENVOLVIMENTO | B12: Moderado | C12: DESENVOLVIMENTO | D12: 0.1
A13: =B13&"-"&C13 -> Moderado-HOTELARIAS | B13: Moderado | C13: HOTELARIAS | D13: 0.1
A14: =B14&"-"&C14 -> Agressivo-PAPEL | B14: Agressivo | C14: PAPEL | D14: 0.5
A15: =B15&"-"&C15 -> Agressivo-TIJOLO | B15: Agressivo | C15: TIJOLO | D15: 0.1
... A19: =B19&"-"&C19 -> Agressivo-HOTELARIAS | B19: Agressivo | C19: HOTELARIAS | D19: 0.1
